Instruction_Memory.v


module Instruction_Memory(rst,A,RD);

  input rst;
  input [31:0]A;
  output [31:0]RD;

  reg [31:0] mem [1023:0];
  
  assign RD = (rst) ? {32{1'b0}} : mem[A[31:2]];

  initial begin
    $readmemh("memfile.hex",mem);
  end


/*
  initial begin
    //mem[0] = 32'hFFC4A303;
    //mem[1] = 32'h00832383;
    // mem[0] = 32'h0064A423;
    // mem[1] = 32'h00B62423;
    mem[0] = 32'h0062E233;
    // mem[1] = 32'h00B62423;

  end
*/
endmodule

PC_Adder.v
`ifndef PC_ADDER_V
`define PC_ADDER_V

module PC_Adder (a,b,c);

    input [31:0]a,b;
    output [31:0]c;

    assign c = a + b;
    
endmodule
`endif

PC.v


module PC_Module(clk,rst,PC,PC_Next);
    input clk,rst;
    input [31:0]PC_Next;
    output [31:0]PC;
    reg [31:0]PC;

    always @(posedge clk)
    begin
        if(rst==1'b1)
            PC <= {32{1'b0}};
        else
            PC <= PC_Next;
    end
endmodule

Mux.v
`ifndef MUX_V 
`define MUX_V
module Mux (a,b,s,c);

    input [31:0]a,b;
    input s;
    output [31:0]c;

    assign c = (~s) ? a : b ;
    
endmodule
`endif

Fetch_Cycle.v
`include "Mux.v"
`include "PC.v"
`include "PC_Adder.v"
`include "Instruction_Memory.v"
module fetch_cycle(input clk ,input rst , input PCSrcE, input [31:0] PCTargetE,output [31:0] InstrD, output [31:0] PCD, output [31:0]  PCPlus4D);
// module variables 
wire [31:0] PCPlus4F,PCF,PCF_out,Instr_mem;
// PC Mux
Mux pc_mux (PCPlus4F,PCTargetE,PCSrcE,PCF_out);
// register which stores addr
PC_Module pc_reg(clk,rst,PCF,PCF_out);
// FETCH CYLCLE PIPELINE REGISTER:
reg [31:0] InstrD_F, PCD_F,PCPlus4D_F;
always @(posedge clk) begin
    // if reset , then set all to 0
    if (rst==1'b1) begin
        InstrD_F<=32'h00000000;
        PCD_F<=32'h00000000;
        PCPlus4D_F<=32'h00000000;
    end
    // else assign them the values 
    else begin
        InstrD_F<=Instr_mem;
        PCD_F<=PCF;
        PCPlus4D_F<=PCPlus4F;
    end
end
// Adder which finds pc+4
PC_Adder p1 (PCF,32'h00000004,PCPlus4F);
// instr memory
Instruction_Memory MEM(rst,PCF,Instr_mem);
// fetch stage complete
// now assign the register values to the outputs of the module:
assign InstrD    = (rst == 1'b0) ? InstrD_F : 32'h00000000;
assign PCD       = (rst == 1'b0) ? PCD_F : 32'h00000000;
 assign PCPlus4D = (rst == 1'b0) ? PCPlus4D_F : 32'h00000000;
endmodule

Fetch_Cycle_tb.v
module tb();
// module to test:
// inputs are regs:
reg clk=1,rst,PC_SrcE;
reg [31:0] PCTargetE;
// outputs are wires
wire [31:0] InstrD,PCD,PCPlus4D;
// instantiate module:
fetch_cycle dut(clk,rst,PC_SrcE,PCTargetE,InstrD,PCD,PCPlus4D);
// generate clock
always begin
    clk = ~clk;
    #50;
end
// initliase the control signals :
initial begin
    rst <= 1'b1;
    #300;
    rst <= 1'b0;
    PC_SrcE<=1'b0;
    PCTargetE <= 32'h00000000;
    #500;
    $finish;
end

// create VCD file:
initial begin
    $dumpfile("fetch_dump.vcd");
    $dumpvars(0,tb);
end


endmodule

fetch_dump.vcd
$date
	Sun Apr  6 17:10:26 2025
$end
$version
	Icarus Verilog
$end
$timescale
	1s
$end
$scope module tb $end
$var wire 32 ! PCPlus4D [31:0] $end
$var wire 32 " PCD [31:0] $end
$var wire 32 # InstrD [31:0] $end
$var reg 32 $ PCTargetE [31:0] $end
$var reg 1 % PC_SrcE $end
$var reg 1 & clk $end
$var reg 1 ' rst $end
$scope module dut $end
$var wire 1 % PCSrcE $end
$var wire 32 ( PCTargetE [31:0] $end
$var wire 1 & clk $end
$var wire 1 ' rst $end
$var wire 32 ) PCPlus4F [31:0] $end
$var wire 32 * PCPlus4D [31:0] $end
$var wire 32 + PCF_out [31:0] $end
$var wire 32 , PCF [31:0] $end
$var wire 32 - PCD [31:0] $end
$var wire 32 . Instr_mem [31:0] $end
$var wire 32 / InstrD [31:0] $end
$var reg 32 0 InstrD_F [31:0] $end
$var reg 32 1 PCD_F [31:0] $end
$var reg 32 2 PCPlus4D_F [31:0] $end
$scope module MEM $end
$var wire 1 ' rst $end
$var wire 32 3 RD [31:0] $end
$var wire 32 4 A [31:0] $end
$upscope $end
$scope module p1 $end
$var wire 32 5 b [31:0] $end
$var wire 32 6 c [31:0] $end
$var wire 32 7 a [31:0] $end
$upscope $end
$scope module pc_mux $end
$var wire 32 8 a [31:0] $end
$var wire 32 9 b [31:0] $end
$var wire 1 % s $end
$var wire 32 : c [31:0] $end
$upscope $end
$scope module pc_reg $end
$var wire 32 ; PC_Next [31:0] $end
$var wire 1 & clk $end
$var wire 1 ' rst $end
$var reg 32 < PC [31:0] $end
$upscope $end
$upscope $end
$upscope $end
$enddefinitions $end
$comment Show the parameter values. $end
$dumpall
$end
#0
$dumpvars
bx <
bx ;
bx :
bx 9
bx 8
bx 7
bx 6
b100 5
bx 4
b0 3
bx 2
bx 1
bx 0
b0 /
b0 .
b0 -
bx ,
bx +
b0 *
bx )
bx (
1'
0&
x%
bx $
b0 #
b0 "
b0 !
$end
#50
b0 2
b0 1
b0 0
b100 )
b100 6
b100 8
b0 ,
b0 4
b0 7
b0 <
1&
#100
0&
#150
1&
#200
0&
#250
1&
#300
b100 +
b100 :
b100 ;
b11000101110001110110011 .
b11000101110001110110011 3
b0 $
b0 (
b0 9
0%
0'
0&
#350
b11000101111010000110011 .
b11000101111010000110011 3
b1000 +
b1000 :
b1000 ;
b100 !
b100 *
b11000101110001110110011 #
b11000101110001110110011 /
b1000 )
b1000 6
b1000 8
b100 ,
b100 4
b100 7
b100 <
b100 2
b11000101110001110110011 0
1&
#400
0&
#450
bx .
bx 3
b1000 !
b1000 *
b100 "
b100 -
b11000101111010000110011 #
b11000101111010000110011 /
b1100 +
b1100 :
b1100 ;
b1000 2
b100 1
b11000101111010000110011 0
b1100 )
b1100 6
b1100 8
b1000 ,
b1000 4
b1000 7
b1000 <
1&
#500
0&
#550
b10000 +
b10000 :
b10000 ;
b1100 !
b1100 *
b1000 "
b1000 -
bx #
bx /
b10000 )
b10000 6
b10000 8
b1100 ,
b1100 4
b1100 7
b1100 <
b1100 2
b1000 1
bx 0
1&
#600
0&
#650
b10000 !
b10000 *
b1100 "
b1100 -
b10100 +
b10100 :
b10100 ;
b10000 2
b1100 1
b10100 )
b10100 6
b10100 8
b10000 ,
b10000 4
b10000 7
b10000 <
1&
#700
0&
#750
b11000 +
b11000 :
b11000 ;
b10100 !
b10100 *
b10000 "
b10000 -
b11000 )
b11000 6
b11000 8
b10100 ,
b10100 4
b10100 7
b10100 <
b10100 2
b10000 1
1&
